slime_volleyball/__init__.py
slime_volleyball/baseline_policy.py
slime_volleyball/rendering.py
slime_volleyball/slimevolley_boost_env.py
slime_volleyball/slimevolley_env.py
slime_volleyball/core/__init__.py
slime_volleyball/core/agent.py
slime_volleyball/core/constants.py
slime_volleyball/core/game.py
slime_volleyball/core/objects.py
slime_volleyball/core/utils.py
slimevb-0.1.0.dist-info/METADATA
slimevb-0.1.0.dist-info/WHEEL
slimevb-0.1.0.dist-info/top_level.txt
slimevb-0.1.0.dist-info/RECORD
